{
  "basics": {
    "name": "MADHAV RAJESH",
    "label": "Master of Science in Computer Science Student",
    "email": "madhavrajesh.cs@gmail.com",
    "phone": "(858)-744-1351",
    "url": "https://github.com/maddyrajesh",
    "summary": "A proactive Master of Science in Computer Science student specializing in algorithms, cloud computing, and quantum computing. Experienced in software development and research with a robust foundation in data structures, machine learning, and full-stack development.",
    "location": {
      "address": "Phoenix, AZ",
      "postalCode": "",
      "city": "Phoenix",
      "countryCode": "US",
      "region": "Arizona"
    },
    "profiles": [
      {
        "network": "LinkedIn",
        "username": "madhavrajesh",
        "url": "https://linkedin.com/in/madhavrajesh"
      },
      {
        "network": "GitHub",
        "username": "maddyrajesh",
        "url": "https://github.com/maddyrajesh"
      }
    ]
  },
  "education": [
    {
      "institution": "Arizona State University",
      "area": "Computer Science",
      "studyType": "Master of Science",
      "startDate": "2022",
      "endDate": "2024",
      "gpa": "3.26/4.00",
      "courses": [
        "Algorithms",
        "Advanced Networks",
        "Combinatorics and Optimization",
        "Cloud Computing",
        "Quantum Computing"
      ]
    },
    {
      "institution": "Vellore Institute of Technology",
      "area": "Information Technology",
      "studyType": "Bachelor of Technology",
      "startDate": "2018",
      "endDate": "2022",
      "gpa": "8.23/10.00",
      "courses": [
        "Data Structures",
        "Database Management System",
        "Computer Networks",
        "Operating Systems",
        "Machine Learning"
      ]
    }
  ],
  "work": [
    {
      "company": "Vellore Institute of Technology",
      "position": "Undergraduate Researcher",
      "startDate": "2021-01",
      "endDate": "2022-05",
      "summary": "Trained a CNN-RF model for real-time processing of rainforest audio; deployed an alert system with recycled phones for threat detection; achieved a 92.7% accuracy.",
      "highlights": [
        "Processed 17,000+ hours of Rainforest Audio in real time.",
        "Deployed an alert system instantly detecting threats such as chainsaws and trucks.",
        "Achieved a 92.7% accuracy, surpassing benchmarks."
      ]
    },
    {
      "company": "FreshToHome",
      "position": "Software Engineer, Intern",
      "startDate": "2021-02",
      "endDate": "2021-05",
      "summary": "Optimized a recommendation engine using RNN models for 1.5 million active users; implemented real-time data solutions with Redis Streams and Apache Spark.",
      "highlights": [
        "Enhanced user experience by optimizing recommendation engine.",
        "Achieved sub-20ms latency with real-time data solutions.",
        "Boosted user engagement and session duration."
      ]
    }
  ],
  "projects": [
    {
      "name": "Hybrid Cloud for Smart Education",
      "description": "Engineered a scalable AWS Lambda-based application for live classroom video footage processing; utilized Ceph for object storage.",
      "highlights": [
        "Handled 10,000+ video hours with 99.6% accuracy in student identification.",
        "Reduced response times by 40% using OpenFaaS on Kubernetes.",
        "Supported 5 TB of video data with enhanced data throughput by 50%."
      ],
      "keywords": ["AWS Lambda", "Kubernetes", "Ceph"],
      "startDate": "2023-07",
      "endDate": "2023-12"
    },
    {
      "name": "P4 DDoS Attack Detection",
      "description": "Developed a P4-based DDoS detection system; showcased effectiveness on the FABRIC testbed with over 5 million requests per second.",
      "highlights": [
        "Achieved 98.2% threat detection with minimal delay.",
        "Identified 96% of attack packets with improved hashing.",
        "Validated scalability and effectiveness on the FABRIC testbed."
      ],
      "keywords": ["P4", "DDoS Detection", "FABRIC testbed"],
      "startDate": "2023-01",
      "endDate": "2023-05"
    }
  ],
  "skills": [
    {
      "name": "Technical Skills",
      "level": "",
      "keywords": [
        "Python", "C", "C#", "C++", "HTML", "CSS", "JavaScript", "Java", "Kotlin", "Dart", "MATLAB", "Go", "Rust", "P4",
        "React.js", "Node.js", "Express.js", "Flask", "scikit-learn", "Keras", "TensorFlow", "NumPy", "pandas", "PyTorch",
        "Git", "Linux", "AWS", "SQL", "MongoDB", "JWT", "CI/CD"
      ]
    }
  ],
  "volunteer": [
    {
      "organization": "IEEE VIT Vellore",
      "position": "Vice-Chairperson",
      "startDate": "2021-01",
      "endDate": "2021-12",
      "summary": "Led a cross-functional team of 80 students in technical projects, organizing hackathons and workshops on Machine Learning and Web Development.",
      "highlights": [
        "Led cross-functional team of 80 students in technical projects.",
        "Organized 5 hackathons and 36 workshops, impacting 1,000+ students each semester."
      ]
    }
  ]
}
